{
  "INFO": {
    "URL": "https://github.com/Angelica2001143/WebDev-InventorySystem/blob/f2324476691668ee0bc7483e389b81ad8adb685b/db/inventory_project.sql?raw=true\n",
    "LICENSE": "MIT",
    "PERMISSIVE": true
  },
  "TABLES": {
    "archive": {
      "COLUMNS": {
        "id": {
          "TYPE": "Int",
          "NULLABLE": false,
          "UNIQUE": true,
          "DEFAULT": null,
          "CHECKS": [],
          "IS_PRIMARY": true,
          "IS_INDEX": false,
          "COMMENT": null
        },
        "name": {
          "TYPE": "Varchar",
          "NULLABLE": false,
          "UNIQUE": null,
          "DEFAULT": null,
          "CHECKS": [],
          "IS_PRIMARY": false,
          "IS_INDEX": false,
          "COMMENT": null
        },
        "bought": {
          "TYPE": "Int",
          "NULLABLE": false,
          "UNIQUE": null,
          "DEFAULT": null,
          "CHECKS": [],
          "IS_PRIMARY": false,
          "IS_INDEX": false,
          "COMMENT": null
        },
        "sold": {
          "TYPE": "Int",
          "NULLABLE": false,
          "UNIQUE": null,
          "DEFAULT": null,
          "CHECKS": [],
          "IS_PRIMARY": false,
          "IS_INDEX": false,
          "COMMENT": null
        },
        "image": {
          "TYPE": "Varchar",
          "NULLABLE": false,
          "UNIQUE": null,
          "DEFAULT": null,
          "CHECKS": [],
          "IS_PRIMARY": false,
          "IS_INDEX": false,
          "COMMENT": null
        },
        "created_at": {
          "TYPE": "Datetime",
          "NULLABLE": null,
          "UNIQUE": null,
          "DEFAULT": null,
          "CHECKS": [],
          "IS_PRIMARY": false,
          "IS_INDEX": false,
          "COMMENT": null
        },
        "updated_at": {
          "TYPE": "Datetime",
          "NULLABLE": false,
          "UNIQUE": null,
          "DEFAULT": null,
          "CHECKS": [],
          "IS_PRIMARY": false,
          "IS_INDEX": false,
          "COMMENT": null
        }
      },
      "PRIMARY_KEYS": [
        "id"
      ],
      "FOREIGN_KEYS": [],
      "CHECKS": [],
      "INDEXES": [],
      "COMMENT": null
    },
    "customers_info": {
      "COLUMNS": {
        "id": {
          "TYPE": "Int",
          "NULLABLE": false,
          "UNIQUE": true,
          "DEFAULT": null,
          "CHECKS": [],
          "IS_PRIMARY": true,
          "IS_INDEX": false,
          "VALUES": [
            4,
            5,
            6,
            7,
            8,
            9,
            11
          ],
          "COMMENT": null
        },
        "name": {
          "TYPE": "Varchar",
          "NULLABLE": false,
          "UNIQUE": null,
          "DEFAULT": null,
          "CHECKS": [],
          "IS_PRIMARY": false,
          "IS_INDEX": false,
          "VALUES": [
            "<PERSON>",
            "<PERSON>",
            "<PERSON>",
            "<PERSON>",
            "<PERSON>",
            "<PERSON>",
            "Angie"
          ],
          "COMMENT": null
        },
        "type": {
          "TYPE": "Varchar",
          "NULLABLE": false,
          "UNIQUE": null,
          "DEFAULT": "new",
          "CHECKS": [],
          "IS_PRIMARY": false,
          "IS_INDEX": false,
          "VALUES": [
            "Regular",
            "New",
            "New",
            "New",
            "New",
            "Regular",
            "Regular"
          ],
          "COMMENT": null
        },
        "email": {
          "TYPE": "Varchar",
          "NULLABLE": null,
          "UNIQUE": null,
          "DEFAULT": null,
          "CHECKS": [],
          "IS_PRIMARY": false,
          "IS_INDEX": false,
          "VALUES": [
            "<EMAIL_ADDRESS>",
            "<EMAIL_ADDRESS>",
            "<EMAIL_ADDRESS>",
            "<EMAIL_ADDRESS>",
            "<EMAIL_ADDRESS>",
            "<EMAIL_ADDRESS>",
            "<EMAIL_ADDRESS>"
          ],
          "COMMENT": null
        },
        "current_orders": {
          "TYPE": "Varchar",
          "NULLABLE": null,
          "UNIQUE": null,
          "DEFAULT": null,
          "CHECKS": [],
          "IS_PRIMARY": false,
          "IS_INDEX": false,
          "VALUES": [
            "12 items",
            "3 items",
            "4 items",
            "5 items",
            "7 items",
            "10 items",
            "12 items"
          ],
          "COMMENT": null
        },
        "shipping_address": {
          "TYPE": "Varchar",
          "NULLABLE": false,
          "UNIQUE": null,
          "DEFAULT": null,
          "CHECKS": [],
          "IS_PRIMARY": false,
          "IS_INDEX": false,
          "VALUES": [
            "<PERSON>",
            "<PERSON>",
            "<PERSON>",
            "<LOCATION>",
            "<PERSON>",
            "<PERSON>",
            "<PERSON>"
          ],
          "COMMENT": null
        },
        "avatar": {
          "TYPE": "Varchar",
          "NULLABLE": null,
          "UNIQUE": null,
          "DEFAULT": null,
          "CHECKS": [],
          "IS_PRIMARY": false,
          "IS_INDEX": false,
          "VALUES": [
            "Customers/pro3.png",
            "Customers/capture.png",
            "Customers/cute.png",
            "Customers/cutest.png",
            "Customers/isogkakol.png",
            "Customers/ericka.png",
            "Customers/hmmm.jpg"
          ],
          "COMMENT": null
        }
      },
      "PRIMARY_KEYS": [
        "id"
      ],
      "FOREIGN_KEYS": [],
      "CHECKS": [],
      "INDEXES": [],
      "COMMENT": null
    },
    "products": {
      "COLUMNS": {
        "id": {
          "TYPE": "Int",
          "NULLABLE": false,
          "UNIQUE": true,
          "DEFAULT": null,
          "CHECKS": [],
          "IS_PRIMARY": true,
          "IS_INDEX": false,
          "VALUES": [
            22,
            23,
            24,
            28,
            30,
            31,
            32,
            33
          ],
          "COMMENT": null
        },
        "name": {
          "TYPE": "Varchar",
          "NULLABLE": false,
          "UNIQUE": null,
          "DEFAULT": null,
          "CHECKS": [],
          "IS_PRIMARY": false,
          "IS_INDEX": false,
          "VALUES": [
            "<PERSON>",
            "Milk Powder",
            "Soap Bar",
            "Tooth Paste",
            "Sunscreen",
            "Green Tea",
            "Glucose",
            "Body Lotion"
          ],
          "COMMENT": null
        },
        "bought": {
          "TYPE": "Int",
          "NULLABLE": false,
          "UNIQUE": null,
          "DEFAULT": null,
          "CHECKS": [],
          "IS_PRIMARY": false,
          "IS_INDEX": false,
          "VALUES": [
            61,
            40,
            100,
            80,
            56,
            50,
            200,
            58
          ],
          "COMMENT": null
        },
        "sold": {
          "TYPE": "Int",
          "NULLABLE": false,
          "UNIQUE": null,
          "DEFAULT": null,
          "CHECKS": [],
          "IS_PRIMARY": false,
          "IS_INDEX": false,
          "VALUES": [
            20,
            5,
            20,
            30,
            11,
            40,
            40,
            0
          ],
          "COMMENT": null
        },
        "image": {
          "TYPE": "Varchar",
          "NULLABLE": false,
          "UNIQUE": null,
          "DEFAULT": null,
          "CHECKS": [],
          "IS_PRIMARY": false,
          "IS_INDEX": false,
          "VALUES": [
            "Uploads/hand-removebg-preview.png",
            "Uploads/milk-removebg-preview.png",
            "Uploads/soap-removebg-preview.png",
            "Uploads/toothpaste-removebg-preview.png",
            "Uploads/sun-removebg-preview.png",
            "Uploads/green-removebg-preview.png",
            "Uploads/glucose-removebg-preview.png",
            "Uploads/body-removebg-preview.png"
          ],
          "COMMENT": null
        },
        "archive": {
          "TYPE": "Int",
          "NULLABLE": false,
          "UNIQUE": null,
          "DEFAULT": null,
          "CHECKS": [],
          "IS_PRIMARY": false,
          "IS_INDEX": false,
          "VALUES": [
            0,
            1,
            0,
            0,
            0,
            0,
            0,
            1
          ],
          "COMMENT": null
        },
        "created_at": {
          "TYPE": "Datetime",
          "NULLABLE": null,
          "UNIQUE": null,
          "DEFAULT": null,
          "CHECKS": [],
          "IS_PRIMARY": false,
          "IS_INDEX": false,
          "VALUES": [
            "2021-03-30 13:34:45",
            "2021-03-30 13:35:07",
            "2021-03-30 13:38:01",
            "2021-03-30 15:16:45",
            "2021-03-31 01:32:14",
            "2021-03-31 01:43:42",
            "2021-03-31 01:45:21",
            "2021-04-04 23:08:38"
          ],
          "COMMENT": null
        },
        "updated_at": {
          "TYPE": "Datetime",
          "NULLABLE": false,
          "UNIQUE": null,
          "DEFAULT": null,
          "CHECKS": [],
          "IS_PRIMARY": false,
          "IS_INDEX": false,
          "VALUES": [
            "2021-03-30 13:34:45",
            "2021-03-30 13:35:07",
            "2021-03-30 13:38:01",
            "2021-03-30 15:16:45",
            "2021-03-31 01:32:14",
            "2021-04-08 11:43:42",
            "2021-03-31 01:45:21",
            "2021-04-04 23:08:38"
          ],
          "COMMENT": null
        }
      },
      "PRIMARY_KEYS": [
        "id"
      ],
      "FOREIGN_KEYS": [],
      "CHECKS": [],
      "INDEXES": [],
      "COMMENT": null
    },
    "request": {
      "COLUMNS": {
        "id": {
          "TYPE": "Int",
          "NULLABLE": false,
          "UNIQUE": null,
          "DEFAULT": null,
          "CHECKS": [],
          "IS_PRIMARY": false,
          "IS_INDEX": false,
          "VALUES": [
            1,
            2,
            3,
            4,
            5,
            6
          ],
          "COMMENT": null
        },
        "product_id": {
          "TYPE": "Int",
          "NULLABLE": false,
          "UNIQUE": null,
          "DEFAULT": null,
          "CHECKS": [],
          "IS_PRIMARY": false,
          "IS_INDEX": false,
          "VALUES": [
            22,
            30,
            30,
            23,
            24,
            22
          ],
          "COMMENT": null
        },
        "name": {
          "TYPE": "Varchar",
          "NULLABLE": false,
          "UNIQUE": null,
          "DEFAULT": null,
          "CHECKS": [],
          "IS_PRIMARY": false,
          "IS_INDEX": false,
          "VALUES": [
            "<PERSON>",
            "<PERSON>",
            "<PERSON>",
            "<PERSON>",
            "<PERSON>",
            "<PERSON>"
          ],
          "COMMENT": null
        },
        "message": {
          "TYPE": "Varchar",
          "NULLABLE": false,
          "UNIQUE": null,
          "DEFAULT": null,
          "CHECKS": [],
          "IS_PRIMARY": false,
          "IS_INDEX": false,
          "VALUES": [
            "Oi",
            "hoy, unsa mani nga products ouy?",
            "Hi po heheheh",
            "Akong request kay unta makabarato mi ana. Suggest ko lang. Malapit na kasi ang pasko.",
            "Hoy, bati ug picture imong product. Effective na?",
            "<PERSON>"
          ],
          "COMMENT": null
        }
      },
      "PRIMARY_KEYS": [],
      "FOREIGN_KEYS": [
        {
          "COLUMNS": [
            "product_id"
          ],
          "FOREIGN_TABLE": "products",
          "REFERRED_COLUMNS": [
            "id"
          ],
          "ON_DELETE": "Cascade",
          "ON_UPDATE": "Cascade"
        }
      ],
      "CHECKS": [],
      "INDEXES": [],
      "COMMENT": null
    },
    "users": {
      "COLUMNS": {
        "id": {
          "TYPE": "Int",
          "NULLABLE": false,
          "UNIQUE": true,
          "DEFAULT": null,
          "CHECKS": [],
          "IS_PRIMARY": true,
          "IS_INDEX": false,
          "VALUES": [
            1
          ],
          "COMMENT": null
        },
        "username": {
          "TYPE": "Varchar",
          "NULLABLE": false,
          "UNIQUE": null,
          "DEFAULT": null,
          "CHECKS": [],
          "IS_PRIMARY": false,
          "IS_INDEX": false,
          "VALUES": [
            "admin"
          ],
          "COMMENT": null
        },
        "password": {
          "TYPE": "Varchar",
          "NULLABLE": false,
          "UNIQUE": null,
          "DEFAULT": null,
          "CHECKS": [],
          "IS_PRIMARY": false,
          "IS_INDEX": false,
          "VALUES": [
            "admin123"
          ],
          "COMMENT": null
        }
      },
      "PRIMARY_KEYS": [
        "id"
      ],
      "FOREIGN_KEYS": [],
      "CHECKS": [],
      "INDEXES": [],
      "COMMENT": null
    },
    "users_info": {
      "COLUMNS": {
        "id": {
          "TYPE": "Int",
          "NULLABLE": false,
          "UNIQUE": true,
          "DEFAULT": null,
          "CHECKS": [],
          "IS_PRIMARY": true,
          "IS_INDEX": false,
          "VALUES": [
            34,
            35,
            36
          ],
          "COMMENT": null
        },
        "name": {
          "TYPE": "Varchar",
          "NULLABLE": false,
          "UNIQUE": null,
          "DEFAULT": null,
          "CHECKS": [],
          "IS_PRIMARY": false,
          "IS_INDEX": false,
          "VALUES": [
            "<PERSON>",
            "<PERSON>",
            "<PERSON>"
          ],
          "COMMENT": null
        },
        "u_name": {
          "TYPE": "Varchar",
          "NULLABLE": false,
          "UNIQUE": null,
          "DEFAULT": null,
          "CHECKS": [],
          "IS_PRIMARY": false,
          "IS_INDEX": false,
          "VALUES": [
            "<PERSON>",
            "<PERSON>",
            "ean"
          ],
          "COMMENT": null
        },
        "email": {
          "TYPE": "Varchar",
          "NULLABLE": null,
          "UNIQUE": null,
          "DEFAULT": null,
          "CHECKS": [],
          "IS_PRIMARY": false,
          "IS_INDEX": false,
          "VALUES": [
            "<EMAIL_ADDRESS>",
            "<EMAIL_ADDRESS>",
            "<EMAIL_ADDRESS>"
          ],
          "COMMENT": null
        },
        "password": {
          "TYPE": "Varchar",
          "NULLABLE": false,
          "UNIQUE": null,
          "DEFAULT": null,
          "CHECKS": [],
          "IS_PRIMARY": false,
          "IS_INDEX": false,
          "VALUES": [
            "161ebd7d45089b3446ee4e0d86dbcf92",
            "161ebd7d45089b3446ee4e0d86dbcf92",
            "161ebd7d45089b3446ee4e0d86dbcf92"
          ],
          "COMMENT": null
        },
        "is_active": {
          "TYPE": "TinyInt",
          "NULLABLE": false,
          "UNIQUE": null,
          "DEFAULT": null,
          "CHECKS": [],
          "IS_PRIMARY": false,
          "IS_INDEX": false,
          "VALUES": [
            1,
            1,
            1
          ],
          "COMMENT": null
        },
        "is_admin": {
          "TYPE": "TinyInt",
          "NULLABLE": false,
          "UNIQUE": null,
          "DEFAULT": null,
          "CHECKS": [],
          "IS_PRIMARY": false,
          "IS_INDEX": false,
          "VALUES": [
            0,
            1,
            0
          ],
          "COMMENT": null
        },
        "avatar": {
          "TYPE": "Varchar",
          "NULLABLE": null,
          "UNIQUE": null,
          "DEFAULT": null,
          "CHECKS": [],
          "IS_PRIMARY": false,
          "IS_INDEX": false,
          "VALUES": [
            "Users/angelica.jfif",
            "Users/dscf2617.jpg",
            "Users/ean.jfif"
          ],
          "COMMENT": null
        },
        "last_login_time": {
          "TYPE": "Timestamp",
          "NULLABLE": false,
          "UNIQUE": null,
          "DEFAULT": null,
          "CHECKS": [],
          "IS_PRIMARY": false,
          "IS_INDEX": false,
          "VALUES": [
            "2021-05-29 13:35:23",
            "2021-05-29 13:41:35",
            "2021-05-29 13:41:12"
          ],
          "COMMENT": null
        },
        "created_at": {
          "TYPE": "Datetime",
          "NULLABLE": false,
          "UNIQUE": null,
          "DEFAULT": null,
          "CHECKS": [],
          "IS_PRIMARY": false,
          "IS_INDEX": false,
          "VALUES": [
            "2021-05-25 16:00:29",
            "2021-05-25 16:05:50",
            "2021-05-25 17:48:15"
          ],
          "COMMENT": null
        }
      },
      "PRIMARY_KEYS": [
        "id"
      ],
      "FOREIGN_KEYS": [],
      "CHECKS": [],
      "INDEXES": [],
      "COMMENT": null
    }
  }
}