{
  "INFO": {
    "URL": "https://github.com/shamgarphp/glm/blob/c1b09fa4e16f7d9c057e176d22eeab35f3740391/siva.sql?raw=true\n",
    "LICENSE": "MIT",
    "PERMISSIVE": true
  },
  "TABLES": {
    "activities": {
      "COLUMNS": {
        "activity_id": {
          "TYPE": "Int",
          "NULLABLE": false,
          "UNIQUE": true,
          "DEFAULT": null,
          "CHECKS": [],
          "IS_PRIMARY": true,
          "IS_INDEX": false,
          "COMMENT": null
        },
        "activity_name": {
          "TYPE": "Varchar",
          "NULLABLE": false,
          "UNIQUE": null,
          "DEFAULT": null,
          "CHECKS": [],
          "IS_PRIMARY": false,
          "IS_INDEX": false,
          "COMMENT": null
        },
        "image": {
          "TYPE": "Text",
          "NULLABLE": false,
          "UNIQUE": null,
          "DEFAULT": null,
          "CHECKS": [],
          "IS_PRIMARY": false,
          "IS_INDEX": false,
          "COMMENT": null
        },
        "status": {
          "TYPE": "Int",
          "NULLABLE": false,
          "UNIQUE": null,
          "DEFAULT": null,
          "CHECKS": [],
          "IS_PRIMARY": false,
          "IS_INDEX": false,
          "COMMENT": "1=active  ,  0=inactive"
        },
        "created_on": {
          "TYPE": "Datetime",
          "NULLABLE": false,
          "UNIQUE": null,
          "DEFAULT": null,
          "CHECKS": [],
          "IS_PRIMARY": false,
          "IS_INDEX": false,
          "COMMENT": null
        },
        "updated_on": {
          "TYPE": "Datetime",
          "NULLABLE": false,
          "UNIQUE": null,
          "DEFAULT": null,
          "CHECKS": [],
          "IS_PRIMARY": false,
          "IS_INDEX": false,
          "COMMENT": null
        },
        "title_id": {
          "TYPE": "Int",
          "NULLABLE": false,
          "UNIQUE": null,
          "DEFAULT": null,
          "CHECKS": [],
          "IS_PRIMARY": false,
          "IS_INDEX": false,
          "COMMENT": null
        },
        "dept_no": {
          "TYPE": "Int",
          "NULLABLE": false,
          "UNIQUE": null,
          "DEFAULT": null,
          "CHECKS": [],
          "IS_PRIMARY": false,
          "IS_INDEX": false,
          "COMMENT": null
        },
        "subject_aim": {
          "TYPE": "Text",
          "NULLABLE": false,
          "UNIQUE": null,
          "DEFAULT": null,
          "CHECKS": [],
          "IS_PRIMARY": false,
          "IS_INDEX": false,
          "COMMENT": null
        },
        "implemented_by": {
          "TYPE": "Int",
          "NULLABLE": false,
          "UNIQUE": null,
          "DEFAULT": null,
          "CHECKS": [],
          "IS_PRIMARY": false,
          "IS_INDEX": false,
          "COMMENT": null
        }
      },
      "PRIMARY_KEYS": [
        "activity_id"
      ],
      "FOREIGN_KEYS": [],
      "CHECKS": [],
      "INDEXES": [],
      "COMMENT": null
    },
    "admin": {
      "COLUMNS": {
        "admin_id": {
          "TYPE": "Int",
          "NULLABLE": false,
          "UNIQUE": true,
          "DEFAULT": null,
          "CHECKS": [],
          "IS_PRIMARY": true,
          "IS_INDEX": false,
          "VALUES": [
            1
          ],
          "COMMENT": null
        },
        "name": {
          "TYPE": "Varchar",
          "NULLABLE": false,
          "UNIQUE": null,
          "DEFAULT": null,
          "CHECKS": [],
          "IS_PRIMARY": false,
          "IS_INDEX": false,
          "VALUES": [
            "Admin"
          ],
          "COMMENT": null
        },
        "email": {
          "TYPE": "Varchar",
          "NULLABLE": false,
          "UNIQUE": null,
          "DEFAULT": null,
          "CHECKS": [],
          "IS_PRIMARY": false,
          "IS_INDEX": false,
          "VALUES": [
            "<EMAIL_ADDRESS>"
          ],
          "COMMENT": null
        },
        "password": {
          "TYPE": "Varchar",
          "NULLABLE": false,
          "UNIQUE": null,
          "DEFAULT": null,
          "CHECKS": [],
          "IS_PRIMARY": false,
          "IS_INDEX": false,
          "VALUES": [
            "MTIzNDU2"
          ],
          "COMMENT": null
        },
        "created_on": {
          "TYPE": "Datetime",
          "NULLABLE": false,
          "UNIQUE": null,
          "DEFAULT": null,
          "CHECKS": [],
          "IS_PRIMARY": false,
          "IS_INDEX": false,
          "VALUES": [
            "2018-12-19 09:44:45"
          ],
          "COMMENT": null
        },
        "updated_on": {
          "TYPE": "Datetime",
          "NULLABLE": false,
          "UNIQUE": null,
          "DEFAULT": null,
          "CHECKS": [],
          "IS_PRIMARY": false,
          "IS_INDEX": false,
          "VALUES": [
            "0000-00-00 00:00:00"
          ],
          "COMMENT": null
        }
      },
      "PRIMARY_KEYS": [
        "admin_id"
      ],
      "FOREIGN_KEYS": [],
      "CHECKS": [],
      "INDEXES": [],
      "COMMENT": null
    },
    "departments": {
      "COLUMNS": {
        "dept_id": {
          "TYPE": "Int",
          "NULLABLE": false,
          "UNIQUE": true,
          "DEFAULT": null,
          "CHECKS": [],
          "IS_PRIMARY": true,
          "IS_INDEX": false,
          "VALUES": [
            1,
            2,
            3,
            4,
            5,
            6,
            7,
            8
          ],
          "COMMENT": null
        },
        "dept_name": {
          "TYPE": "Varchar",
          "NULLABLE": false,
          "UNIQUE": null,
          "DEFAULT": null,
          "CHECKS": [],
          "IS_PRIMARY": false,
          "IS_INDEX": false,
          "VALUES": [
            "Administration",
            "Children",
            "Education",
            "Church",
            "SEA",
            "Youth",
            "<PERSON>",
            "DCF"
          ],
          "COMMENT": null
        },
        "created_on": {
          "TYPE": "Datetime",
          "NULLABLE": false,
          "UNIQUE": null,
          "DEFAULT": null,
          "CHECKS": [],
          "IS_PRIMARY": false,
          "IS_INDEX": false,
          "VALUES": [
            "0000-00-00 00:00:00",
            "0000-00-00 00:00:00",
            "0000-00-00 00:00:00",
            "0000-00-00 00:00:00",
            "0000-00-00 00:00:00",
            "0000-00-00 00:00:00",
            "0000-00-00 00:00:00",
            "0000-00-00 00:00:00"
          ],
          "COMMENT": null
        },
        "updated_on": {
          "TYPE": "Datetime",
          "NULLABLE": false,
          "UNIQUE": null,
          "DEFAULT": null,
          "CHECKS": [],
          "IS_PRIMARY": false,
          "IS_INDEX": false,
          "VALUES": [
            "0000-00-00 00:00:00",
            "0000-00-00 00:00:00",
            "0000-00-00 00:00:00",
            "0000-00-00 00:00:00",
            "0000-00-00 00:00:00",
            "0000-00-00 00:00:00",
            "0000-00-00 00:00:00",
            "0000-00-00 00:00:00"
          ],
          "COMMENT": null
        },
        "status": {
          "TYPE": "Int",
          "NULLABLE": false,
          "UNIQUE": null,
          "DEFAULT": null,
          "CHECKS": [],
          "IS_PRIMARY": false,
          "IS_INDEX": false,
          "VALUES": [
            0,
            0,
            0,
            0,
            0,
            0,
            0,
            0
          ],
          "COMMENT": null
        }
      },
      "PRIMARY_KEYS": [
        "dept_id"
      ],
      "FOREIGN_KEYS": [],
      "CHECKS": [],
      "INDEXES": [],
      "COMMENT": null
    },
    "dept_emp": {
      "COLUMNS": {
        "emp_no": {
          "TYPE": "Int",
          "NULLABLE": false,
          "UNIQUE": null,
          "DEFAULT": null,
          "CHECKS": [],
          "IS_PRIMARY": false,
          "IS_INDEX": false,
          "COMMENT": null
        },
        "dept_no": {
          "TYPE": "Char",
          "NULLABLE": false,
          "UNIQUE": null,
          "DEFAULT": null,
          "CHECKS": [],
          "IS_PRIMARY": false,
          "IS_INDEX": false,
          "COMMENT": null
        },
        "from_date": {
          "TYPE": "Date",
          "NULLABLE": false,
          "UNIQUE": null,
          "DEFAULT": null,
          "CHECKS": [],
          "IS_PRIMARY": false,
          "IS_INDEX": false,
          "COMMENT": null
        },
        "to_date": {
          "TYPE": "Date",
          "NULLABLE": false,
          "UNIQUE": null,
          "DEFAULT": null,
          "CHECKS": [],
          "IS_PRIMARY": false,
          "IS_INDEX": false,
          "COMMENT": null
        }
      },
      "PRIMARY_KEYS": [],
      "FOREIGN_KEYS": [],
      "CHECKS": [],
      "INDEXES": [],
      "COMMENT": null
    },
    "employees": {
      "COLUMNS": {
        "emp_no": {
          "TYPE": "Int",
          "NULLABLE": false,
          "UNIQUE": true,
          "DEFAULT": null,
          "CHECKS": [],
          "IS_PRIMARY": true,
          "IS_INDEX": false,
          "VALUES": [
            1,
            2,
            3,
            4,
            5,
            6,
            7,
            8,
            9,
            10,
            11,
            12,
            13
          ],
          "COMMENT": null
        },
        "birth_date": {
          "TYPE": "Date",
          "NULLABLE": false,
          "UNIQUE": null,
          "DEFAULT": null,
          "CHECKS": [],
          "IS_PRIMARY": false,
          "IS_INDEX": false,
          "VALUES": [
            "0000-00-00",
            "0000-00-00",
            "0000-00-00",
            "0000-00-00",
            "0000-00-00",
            "1970-01-01",
            "2019-01-16",
            "1970-01-01",
            "2019-01-23",
            "1970-01-01",
            "1970-01-01",
            "1970-01-01",
            "2019-01-09"
          ],
          "COMMENT": null
        },
        "first_name": {
          "TYPE": "Varchar",
          "NULLABLE": false,
          "UNIQUE": null,
          "DEFAULT": null,
          "CHECKS": [],
          "IS_PRIMARY": false,
          "IS_INDEX": false,
          "VALUES": [
            "<PERSON>",
            "sai",
            "ravi",
            "siva",
            "anil",
            "teset",
            "<PERSON>",
            "dfsad",
            "rakesh",
            "fasd",
            "ravi",
            "<PERSON>",
            "raju"
          ],
          "COMMENT": null
        },
        "last_name": {
          "TYPE": "Varchar",
          "NULLABLE": false,
          "UNIQUE": null,
          "DEFAULT": null,
          "CHECKS": [],
          "IS_PRIMARY": false,
          "IS_INDEX": false,
          "VALUES": [
            "rao",
            "kumar",
            "kumar",
            "kumar",
            "kumar",
            "",
            "kumar",
            "",
            "kumar",
            "",
            "",
            "",
            "kumar"
          ],
          "COMMENT": null
        },
        "email": {
          "TYPE": "Varchar",
          "NULLABLE": false,
          "UNIQUE": null,
          "DEFAULT": null,
          "CHECKS": [],
          "IS_PRIMARY": false,
          "IS_INDEX": false,
          "VALUES": [
            "",
            "",
            "",
            "",
            "",
            "",
            "<EMAIL_ADDRESS>",
            "",
            "<EMAIL_ADDRESS>",
            "",
            "",
            "",
            "<EMAIL_ADDRESS>"
          ],
          "COMMENT": null
        },
        "password": {
          "TYPE": "Varchar",
          "NULLABLE": false,
          "UNIQUE": null,
          "DEFAULT": null,
          "CHECKS": [],
          "IS_PRIMARY": false,
          "IS_INDEX": false,
          "VALUES": [
            "",
            "",
            "",
            "",
            "",
            "",
            "12345",
            "",
            "12345",
            "",
            "",
            "",
            "6666666"
          ],
          "COMMENT": null
        },
        "gender": {
          "TYPE": "Enum",
          "NULLABLE": false,
          "UNIQUE": null,
          "DEFAULT": null,
          "CHECKS": [],
          "IS_PRIMARY": false,
          "IS_INDEX": false,
          "VALUES": [
            "M",
            "M",
            "M",
            "M",
            "M",
            "M",
            "M",
            "M",
            "M",
            "M",
            "M",
            "M",
            "M"
          ],
          "COMMENT": null
        },
        "hire_date": {
          "TYPE": "Date",
          "NULLABLE": false,
          "UNIQUE": null,
          "DEFAULT": null,
          "CHECKS": [],
          "IS_PRIMARY": false,
          "IS_INDEX": false,
          "VALUES": [
            "0000-00-00",
            "0000-00-00",
            "0000-00-00",
            "0000-00-00",
            "0000-00-00",
            "0000-00-00",
            "0000-00-00",
            "0000-00-00",
            "0000-00-00",
            "0000-00-00",
            "0000-00-00",
            "0000-00-00",
            "0000-00-00"
          ],
          "COMMENT": null
        },
        "father_name": {
          "TYPE": "Varchar",
          "NULLABLE": false,
          "UNIQUE": null,
          "DEFAULT": null,
          "CHECKS": [],
          "IS_PRIMARY": false,
          "IS_INDEX": false,
          "VALUES": [
            "",
            "",
            "",
            "",
            "",
            "",
            "<PERSON>",
            "",
            "<PERSON>",
            "",
            "",
            "",
            "<PERSON>"
          ],
          "COMMENT": null
        },
        "aadhar": {
          "TYPE": "Int",
          "NULLABLE": false,
          "UNIQUE": null,
          "DEFAULT": null,
          "CHECKS": [],
          "IS_PRIMARY": false,
          "IS_INDEX": false,
          "VALUES": [
            0,
            0,
            0,
            0,
            0,
            0,
            "<PHONE_NUMBER>",
            0,
            "<PHONE_NUMBER>",
            0,
            0,
            0,
            "<PHONE_NUMBER>"
          ],
          "COMMENT": null
        },
        "pan_number": {
          "TYPE": "Varchar",
          "NULLABLE": false,
          "UNIQUE": null,
          "DEFAULT": null,
          "CHECKS": [],
          "IS_PRIMARY": false,
          "IS_INDEX": false,
          "VALUES": [
            "",
            "",
            "",
            "",
            "",
            "",
            "65345",
            "",
            "65345",
            "",
            "",
            "",
            "dfasdfas"
          ],
          "COMMENT": null
        },
        "account_name": {
          "TYPE": "Varchar",
          "NULLABLE": false,
          "UNIQUE": null,
          "DEFAULT": null,
          "CHECKS": [],
          "IS_PRIMARY": false,
          "IS_INDEX": false,
          "VALUES": [
            "",
            "",
            "",
            "",
            "",
            "",
            "<PERSON>",
            "",
            "<PERSON>",
            "",
            "",
            "",
            "<PERSON>"
          ],
          "COMMENT": null
        },
        "account_number": {
          "TYPE": "Varchar",
          "NULLABLE": false,
          "UNIQUE": null,
          "DEFAULT": null,
          "CHECKS": [],
          "IS_PRIMARY": false,
          "IS_INDEX": false,
          "VALUES": [
            "",
            "",
            "",
            "",
            "",
            "",
            "63456456454",
            "",
            "63456456454",
            "",
            "",
            "",
            "63456456454"
          ],
          "COMMENT": null
        },
        "ifsc_Code": {
          "TYPE": "Varchar",
          "NULLABLE": false,
          "UNIQUE": null,
          "DEFAULT": null,
          "CHECKS": [],
          "IS_PRIMARY": false,
          "IS_INDEX": false,
          "VALUES": [
            "",
            "",
            "",
            "",
            "",
            "",
            "4345dfd",
            "",
            "4345dfd",
            "",
            "",
            "",
            "4345dfd"
          ],
          "COMMENT": null
        },
        "bank_Name": {
          "TYPE": "Varchar",
          "NULLABLE": false,
          "UNIQUE": null,
          "DEFAULT": null,
          "CHECKS": [],
          "IS_PRIMARY": false,
          "IS_INDEX": false,
          "VALUES": [
            "",
            "",
            "",
            "",
            "",
            "",
            "statebank",
            "",
            "statebank",
            "",
            "",
            "",
            "statebank"
          ],
          "COMMENT": null
        },
        "highest_qualification": {
          "TYPE": "Varchar",
          "NULLABLE": false,
          "UNIQUE": null,
          "DEFAULT": null,
          "CHECKS": [],
          "IS_PRIMARY": false,
          "IS_INDEX": false,
          "VALUES": [
            "",
            "",
            "",
            "",
            "",
            "",
            "BTECH",
            "",
            "be",
            "",
            "",
            "",
            "be"
          ],
          "COMMENT": null
        },
        "job_description": {
          "TYPE": "Varchar",
          "NULLABLE": false,
          "UNIQUE": null,
          "DEFAULT": null,
          "CHECKS": [],
          "IS_PRIMARY": false,
          "IS_INDEX": false,
          "VALUES": [
            "",
            "",
            "",
            "",
            "",
            "",
            "tfdgsfgsdfds",
            "",
            "high_qualhigh_qualhigh_qual",
            "",
            "",
            "",
            "fdsadfsd"
          ],
          "COMMENT": null
        },
        "place_appointment": {
          "TYPE": "Varchar",
          "NULLABLE": false,
          "UNIQUE": null,
          "DEFAULT": null,
          "CHECKS": [],
          "IS_PRIMARY": false,
          "IS_INDEX": false,
          "VALUES": [
            "",
            "",
            "",
            "",
            "",
            "",
            "<LOCATION>",
            "",
            "<LOCATION>",
            "",
            "",
            "",
            "<LOCATION>"
          ],
          "COMMENT": null
        },
        "reporting_to": {
          "TYPE": "Varchar",
          "NULLABLE": false,
          "UNIQUE": null,
          "DEFAULT": null,
          "CHECKS": [],
          "IS_PRIMARY": false,
          "IS_INDEX": false,
          "VALUES": [
            "",
            "",
            "",
            "",
            "",
            "",
            "<PERSON>",
            "",
            "<PERSON>",
            "",
            "",
            "",
            "<PERSON>"
          ],
          "COMMENT": null
        },
        "dev_qualification": {
          "TYPE": "Varchar",
          "NULLABLE": false,
          "UNIQUE": null,
          "DEFAULT": null,
          "CHECKS": [],
          "IS_PRIMARY": false,
          "IS_INDEX": false,
          "VALUES": [
            "",
            "",
            "",
            "",
            "",
            "",
            "extra qulification",
            "",
            "extra qulification",
            "",
            "",
            "",
            "extra qulification"
          ],
          "COMMENT": null
        },
        "disc_profile": {
          "TYPE": "Varchar",
          "NULLABLE": false,
          "UNIQUE": null,
          "DEFAULT": null,
          "CHECKS": [],
          "IS_PRIMARY": false,
          "IS_INDEX": false,
          "VALUES": [
            "",
            "",
            "",
            "",
            "",
            "",
            "",
            "",
            "",
            "",
            "",
            "1a1cdbb734b3a37e96e1ba7ff5d28385.jpg",
            "9a09c1b92a5ae47f82525a1631af623a.jpg"
          ],
          "COMMENT": null
        },
        "role_id": {
          "TYPE": "Int",
          "NULLABLE": false,
          "UNIQUE": null,
          "DEFAULT": null,
          "CHECKS": [],
          "IS_PRIMARY": false,
          "IS_INDEX": false,
          "VALUES": [
            1,
            2,
            3,
            4,
            5,
            0,
            0,
            0,
            0,
            2,
            2,
            2,
            3
          ],
          "COMMENT": null
        },
        "status": {
          "TYPE": "Int",
          "NULLABLE": false,
          "UNIQUE": null,
          "DEFAULT": null,
          "CHECKS": [],
          "IS_PRIMARY": false,
          "IS_INDEX": false,
          "VALUES": [
            1,
            1,
            1,
            1,
            1,
            1,
            1,
            1,
            1,
            1,
            1,
            1,
            1
          ],
          "COMMENT": null
        },
        "created_on": {
          "TYPE": "Datetime",
          "NULLABLE": false,
          "UNIQUE": null,
          "DEFAULT": null,
          "CHECKS": [],
          "IS_PRIMARY": false,
          "IS_INDEX": false,
          "VALUES": [
            "2019-01-03 18:32:50",
            "2019-01-03 18:34:29",
            "2019-01-03 18:35:00",
            "2019-01-03 18:35:08",
            "2019-01-03 18:35:21",
            "2019-01-05 13:33:47",
            "2019-01-05 13:39:10",
            "2019-01-05 15:22:22",
            "2019-01-05 15:25:26",
            "2019-01-05 15:26:49",
            "2019-01-05 15:57:01",
            "2019-01-05 16:06:24",
            "2019-01-05 16:28:22"
          ],
          "COMMENT": null
        },
        "Job_title": {
          "TYPE": "Varchar",
          "NULLABLE": false,
          "UNIQUE": null,
          "DEFAULT": null,
          "CHECKS": [],
          "IS_PRIMARY": false,
          "IS_INDEX": false,
          "VALUES": [
            "",
            "",
            "",
            "",
            "",
            "",
            "",
            "",
            "job-title",
            "",
            "",
            "",
            "job-title"
          ],
          "COMMENT": null
        },
        "department": {
          "TYPE": "Int",
          "NULLABLE": false,
          "UNIQUE": null,
          "DEFAULT": null,
          "CHECKS": [],
          "IS_PRIMARY": false,
          "IS_INDEX": false,
          "VALUES": [
            0,
            0,
            0,
            0,
            0,
            0,
            0,
            0,
            3,
            0,
            0,
            0,
            2
          ],
          "COMMENT": null
        },
        "account_type": {
          "TYPE": "Varchar",
          "NULLABLE": false,
          "UNIQUE": null,
          "DEFAULT": null,
          "CHECKS": [],
          "IS_PRIMARY": false,
          "IS_INDEX": false,
          "VALUES": [
            "",
            "",
            "",
            "",
            "",
            "",
            "",
            "",
            "accounttype",
            "",
            "",
            "",
            "accounttype"
          ],
          "COMMENT": null
        },
        "resume": {
          "TYPE": "Varchar",
          "NULLABLE": false,
          "UNIQUE": null,
          "DEFAULT": null,
          "CHECKS": [],
          "IS_PRIMARY": false,
          "IS_INDEX": false,
          "VALUES": [
            "",
            "",
            "",
            "",
            "",
            "",
            "",
            "",
            "",
            "",
            "",
            "b4c49bea3a7b83ba910814e313e64c02.txt",
            "37af2a10410c7a211310c29f0284332b.txt"
          ],
          "COMMENT": null
        }
      },
      "PRIMARY_KEYS": [
        "emp_no"
      ],
      "FOREIGN_KEYS": [],
      "CHECKS": [],
      "INDEXES": [],
      "COMMENT": null
    },
    "keys": {
      "COLUMNS": {
        "id": {
          "TYPE": "Int",
          "NULLABLE": false,
          "UNIQUE": true,
          "DEFAULT": null,
          "CHECKS": [],
          "IS_PRIMARY": true,
          "IS_INDEX": false,
          "VALUES": [
            1
          ],
          "COMMENT": null
        },
        "user_id": {
          "TYPE": "Int",
          "NULLABLE": false,
          "UNIQUE": null,
          "DEFAULT": null,
          "CHECKS": [],
          "IS_PRIMARY": false,
          "IS_INDEX": false,
          "VALUES": [
            0
          ],
          "COMMENT": null
        },
        "key": {
          "TYPE": "Varchar",
          "NULLABLE": false,
          "UNIQUE": null,
          "DEFAULT": null,
          "CHECKS": [],
          "IS_PRIMARY": false,
          "IS_INDEX": false,
          "VALUES": [
            "SHANKAR@111"
          ],
          "COMMENT": null
        },
        "level": {
          "TYPE": "Int",
          "NULLABLE": false,
          "UNIQUE": null,
          "DEFAULT": null,
          "CHECKS": [],
          "IS_PRIMARY": false,
          "IS_INDEX": false,
          "VALUES": [
            0
          ],
          "COMMENT": null
        },
        "ignore_limits": {
          "TYPE": "TinyInt",
          "NULLABLE": false,
          "UNIQUE": null,
          "DEFAULT": "0",
          "CHECKS": [],
          "IS_PRIMARY": false,
          "IS_INDEX": false,
          "VALUES": [
            0
          ],
          "COMMENT": null
        },
        "is_private_key": {
          "TYPE": "TinyInt",
          "NULLABLE": false,
          "UNIQUE": null,
          "DEFAULT": "0",
          "CHECKS": [],
          "IS_PRIMARY": false,
          "IS_INDEX": false,
          "VALUES": [
            0
          ],
          "COMMENT": null
        },
        "ip_addresses": {
          "TYPE": "Text",
          "NULLABLE": null,
          "UNIQUE": null,
          "DEFAULT": null,
          "CHECKS": [],
          "IS_PRIMARY": false,
          "IS_INDEX": false,
          "VALUES": [
            null
          ],
          "COMMENT": null
        },
        "date_created": {
          "TYPE": "Datetime",
          "NULLABLE": false,
          "UNIQUE": null,
          "DEFAULT": null,
          "CHECKS": [],
          "IS_PRIMARY": false,
          "IS_INDEX": false,
          "VALUES": [
            "2017-10-12 13:34:33"
          ],
          "COMMENT": null
        }
      },
      "PRIMARY_KEYS": [
        "id"
      ],
      "FOREIGN_KEYS": [],
      "CHECKS": [],
      "INDEXES": [],
      "COMMENT": null
    },
    "locations": {
      "COLUMNS": {
        "location_id": {
          "TYPE": "Int",
          "NULLABLE": false,
          "UNIQUE": true,
          "DEFAULT": null,
          "CHECKS": [],
          "IS_PRIMARY": true,
          "IS_INDEX": false,
          "VALUES": [
            8,
            9,
            10,
            11,
            12,
            13,
            14,
            15,
            16,
            17,
            18,
            19,
            20,
            21,
            22,
            23,
            24,
            25
          ],
          "COMMENT": null
        },
        "location": {
          "TYPE": "Varchar",
          "NULLABLE": false,
          "UNIQUE": null,
          "DEFAULT": null,
          "CHECKS": [],
          "IS_PRIMARY": false,
          "IS_INDEX": false,
          "VALUES": [
            "",
            "",
            "",
            "",
            "",
            "",
            "",
            "",
            "",
            "",
            "",
            "",
            "",
            "",
            "",
            "",
            "",
            ""
          ],
          "COMMENT": null
        },
        "area": {
          "TYPE": "Varchar",
          "NULLABLE": false,
          "UNIQUE": null,
          "DEFAULT": null,
          "CHECKS": [],
          "IS_PRIMARY": false,
          "IS_INDEX": false,
          "VALUES": [
            "Iejaa",
            "<PERSON>",
            "<PERSON>",
            "<PERSON>",
            "<LOCATION>",
            "<PERSON>",
            "<PERSON>",
            "<PERSON>",
            "<PERSON>",
            "<PERSON>",
            "<PERSON>",
            "<PERSON>",
            "<PERSON>",
            "<PERSON>",
            "<PERSON>",
            "<PERSON>",
            "<PERSON>",
            "<LOCATION>"
          ],
          "COMMENT": null
        },
        "status": {
          "TYPE": "Int",
          "NULLABLE": false,
          "UNIQUE": null,
          "DEFAULT": null,
          "CHECKS": [],
          "IS_PRIMARY": false,
          "IS_INDEX": false,
          "VALUES": [
            0,
            0,
            0,
            0,
            0,
            0,
            0,
            0,
            0,
            0,
            0,
            0,
            0,
            0,
            0,
            0,
            0,
            0
          ],
          "COMMENT": null
        },
        "created_on": {
          "TYPE": "Datetime",
          "NULLABLE": false,
          "UNIQUE": null,
          "DEFAULT": null,
          "CHECKS": [],
          "IS_PRIMARY": false,
          "IS_INDEX": false,
          "VALUES": [
            "0000-00-00 00:00:00",
            "0000-00-00 00:00:00",
            "0000-00-00 00:00:00",
            "0000-00-00 00:00:00",
            "0000-00-00 00:00:00",
            "0000-00-00 00:00:00",
            "0000-00-00 00:00:00",
            "0000-00-00 00:00:00",
            "0000-00-00 00:00:00",
            "0000-00-00 00:00:00",
            "0000-00-00 00:00:00",
            "0000-00-00 00:00:00",
            "0000-00-00 00:00:00",
            "0000-00-00 00:00:00",
            "0000-00-00 00:00:00",
            "0000-00-00 00:00:00",
            "0000-00-00 00:00:00",
            "0000-00-00 00:00:00"
          ],
          "COMMENT": null
        },
        "updated_on": {
          "TYPE": "Datetime",
          "NULLABLE": false,
          "UNIQUE": null,
          "DEFAULT": null,
          "CHECKS": [],
          "IS_PRIMARY": false,
          "IS_INDEX": false,
          "VALUES": [
            "0000-00-00 00:00:00",
            "0000-00-00 00:00:00",
            "0000-00-00 00:00:00",
            "0000-00-00 00:00:00",
            "0000-00-00 00:00:00",
            "0000-00-00 00:00:00",
            "0000-00-00 00:00:00",
            "0000-00-00 00:00:00",
            "0000-00-00 00:00:00",
            "0000-00-00 00:00:00",
            "0000-00-00 00:00:00",
            "0000-00-00 00:00:00",
            "0000-00-00 00:00:00",
            "0000-00-00 00:00:00",
            "0000-00-00 00:00:00",
            "0000-00-00 00:00:00",
            "0000-00-00 00:00:00",
            "0000-00-00 00:00:00"
          ],
          "COMMENT": null
        }
      },
      "PRIMARY_KEYS": [
        "location_id"
      ],
      "FOREIGN_KEYS": [],
      "CHECKS": [],
      "INDEXES": [],
      "COMMENT": null
    },
    "participants": {
      "COLUMNS": {
        "participant_id": {
          "TYPE": "Int",
          "NULLABLE": false,
          "UNIQUE": null,
          "DEFAULT": null,
          "CHECKS": [],
          "IS_PRIMARY": false,
          "IS_INDEX": false,
          "COMMENT": null
        },
        "participant_type": {
          "TYPE": "Int",
          "NULLABLE": false,
          "UNIQUE": null,
          "DEFAULT": null,
          "CHECKS": [],
          "IS_PRIMARY": false,
          "IS_INDEX": false,
          "COMMENT": null
        },
        "men": {
          "TYPE": "Int",
          "NULLABLE": false,
          "UNIQUE": null,
          "DEFAULT": null,
          "CHECKS": [],
          "IS_PRIMARY": false,
          "IS_INDEX": false,
          "COMMENT": null
        },
        "women": {
          "TYPE": "Int",
          "NULLABLE": false,
          "UNIQUE": null,
          "DEFAULT": null,
          "CHECKS": [],
          "IS_PRIMARY": false,
          "IS_INDEX": false,
          "COMMENT": null
        },
        "child": {
          "TYPE": "Int",
          "NULLABLE": false,
          "UNIQUE": null,
          "DEFAULT": null,
          "CHECKS": [],
          "IS_PRIMARY": false,
          "IS_INDEX": false,
          "COMMENT": null
        },
        "fromdate": {
          "TYPE": "Date",
          "NULLABLE": false,
          "UNIQUE": null,
          "DEFAULT": null,
          "CHECKS": [],
          "IS_PRIMARY": false,
          "IS_INDEX": false,
          "COMMENT": null
        },
        "todate": {
          "TYPE": "Date",
          "NULLABLE": false,
          "UNIQUE": null,
          "DEFAULT": null,
          "CHECKS": [],
          "IS_PRIMARY": false,
          "IS_INDEX": false,
          "COMMENT": null
        },
        "from_time": {
          "TYPE": "Varchar",
          "NULLABLE": false,
          "UNIQUE": null,
          "DEFAULT": null,
          "CHECKS": [],
          "IS_PRIMARY": false,
          "IS_INDEX": false,
          "COMMENT": null
        },
        "to_time": {
          "TYPE": "Varchar",
          "NULLABLE": false,
          "UNIQUE": null,
          "DEFAULT": null,
          "CHECKS": [],
          "IS_PRIMARY": false,
          "IS_INDEX": false,
          "COMMENT": null
        },
        "activity_id": {
          "TYPE": "Int",
          "NULLABLE": false,
          "UNIQUE": null,
          "DEFAULT": null,
          "CHECKS": [],
          "IS_PRIMARY": false,
          "IS_INDEX": false,
          "COMMENT": null
        },
        "name": {
          "TYPE": "Varchar",
          "NULLABLE": false,
          "UNIQUE": null,
          "DEFAULT": null,
          "CHECKS": [],
          "IS_PRIMARY": false,
          "IS_INDEX": false,
          "COMMENT": null
        },
        "phone": {
          "TYPE": "Int",
          "NULLABLE": false,
          "UNIQUE": null,
          "DEFAULT": null,
          "CHECKS": [],
          "IS_PRIMARY": false,
          "IS_INDEX": false,
          "COMMENT": null
        },
        "desccription": {
          "TYPE": "Varchar",
          "NULLABLE": false,
          "UNIQUE": null,
          "DEFAULT": null,
          "CHECKS": [],
          "IS_PRIMARY": false,
          "IS_INDEX": false,
          "COMMENT": null
        }
      },
      "PRIMARY_KEYS": [],
      "FOREIGN_KEYS": [],
      "CHECKS": [],
      "INDEXES": [],
      "COMMENT": null
    },
    "program_staff": {
      "COLUMNS": {
        "program_staff_id": {
          "TYPE": "Int",
          "NULLABLE": false,
          "UNIQUE": true,
          "DEFAULT": null,
          "CHECKS": [],
          "IS_PRIMARY": true,
          "IS_INDEX": false,
          "COMMENT": null
        },
        "location_id": {
          "TYPE": "Int",
          "NULLABLE": false,
          "UNIQUE": null,
          "DEFAULT": null,
          "CHECKS": [],
          "IS_PRIMARY": false,
          "IS_INDEX": false,
          "COMMENT": null
        },
        "program_admin": {
          "TYPE": "Int",
          "NULLABLE": false,
          "UNIQUE": null,
          "DEFAULT": null,
          "CHECKS": [],
          "IS_PRIMARY": false,
          "IS_INDEX": false,
          "COMMENT": null
        },
        "finance_admin": {
          "TYPE": "Int",
          "NULLABLE": false,
          "UNIQUE": null,
          "DEFAULT": null,
          "CHECKS": [],
          "IS_PRIMARY": false,
          "IS_INDEX": false,
          "COMMENT": null
        },
        "report_staff1": {
          "TYPE": "Int",
          "NULLABLE": false,
          "UNIQUE": null,
          "DEFAULT": null,
          "CHECKS": [],
          "IS_PRIMARY": false,
          "IS_INDEX": false,
          "COMMENT": null
        },
        "report_staff2": {
          "TYPE": "Int",
          "NULLABLE": false,
          "UNIQUE": null,
          "DEFAULT": null,
          "CHECKS": [],
          "IS_PRIMARY": false,
          "IS_INDEX": false,
          "COMMENT": null
        },
        "photography": {
          "TYPE": "Int",
          "NULLABLE": false,
          "UNIQUE": null,
          "DEFAULT": null,
          "CHECKS": [],
          "IS_PRIMARY": false,
          "IS_INDEX": false,
          "COMMENT": null
        },
        "created_by": {
          "TYPE": "Int",
          "NULLABLE": false,
          "UNIQUE": null,
          "DEFAULT": null,
          "CHECKS": [],
          "IS_PRIMARY": false,
          "IS_INDEX": false,
          "COMMENT": null
        },
        "created_on": {
          "TYPE": "Datetime",
          "NULLABLE": false,
          "UNIQUE": null,
          "DEFAULT": null,
          "CHECKS": [],
          "IS_PRIMARY": false,
          "IS_INDEX": false,
          "COMMENT": null
        },
        "updated_on": {
          "TYPE": "Datetime",
          "NULLABLE": false,
          "UNIQUE": null,
          "DEFAULT": null,
          "CHECKS": [],
          "IS_PRIMARY": false,
          "IS_INDEX": false,
          "COMMENT": null
        },
        "status": {
          "TYPE": "Int",
          "NULLABLE": false,
          "UNIQUE": null,
          "DEFAULT": null,
          "CHECKS": [],
          "IS_PRIMARY": false,
          "IS_INDEX": false,
          "COMMENT": null
        }
      },
      "PRIMARY_KEYS": [
        "program_staff_id"
      ],
      "FOREIGN_KEYS": [],
      "CHECKS": [],
      "INDEXES": [],
      "COMMENT": null
    },
    "resource_staff": {
      "COLUMNS": {
        "resource_staff_id": {
          "TYPE": "Int",
          "NULLABLE": false,
          "UNIQUE": true,
          "DEFAULT": null,
          "CHECKS": [],
          "IS_PRIMARY": true,
          "IS_INDEX": false,
          "COMMENT": null
        },
        "resource": {
          "TYPE": "Varchar",
          "NULLABLE": false,
          "UNIQUE": null,
          "DEFAULT": null,
          "CHECKS": [],
          "IS_PRIMARY": false,
          "IS_INDEX": false,
          "COMMENT": null
        },
        "program_staff_id": {
          "TYPE": "Int",
          "NULLABLE": false,
          "UNIQUE": null,
          "DEFAULT": null,
          "CHECKS": [],
          "IS_PRIMARY": false,
          "IS_INDEX": false,
          "COMMENT": null
        },
        "created_on": {
          "TYPE": "Datetime",
          "NULLABLE": false,
          "UNIQUE": null,
          "DEFAULT": null,
          "CHECKS": [],
          "IS_PRIMARY": false,
          "IS_INDEX": false,
          "COMMENT": null
        },
        "updated_on": {
          "TYPE": "Datetime",
          "NULLABLE": false,
          "UNIQUE": null,
          "DEFAULT": null,
          "CHECKS": [],
          "IS_PRIMARY": false,
          "IS_INDEX": false,
          "COMMENT": null
        }
      },
      "PRIMARY_KEYS": [
        "resource_staff_id"
      ],
      "FOREIGN_KEYS": [],
      "CHECKS": [],
      "INDEXES": [],
      "COMMENT": null
    },
    "roles": {
      "COLUMNS": {
        "role_id": {
          "TYPE": "Int",
          "NULLABLE": false,
          "UNIQUE": true,
          "DEFAULT": null,
          "CHECKS": [],
          "IS_PRIMARY": true,
          "IS_INDEX": false,
          "VALUES": [
            1,
            2,
            3,
            4,
            5,
            6
          ],
          "COMMENT": null
        },
        "name": {
          "TYPE": "Varchar",
          "NULLABLE": false,
          "UNIQUE": null,
          "DEFAULT": null,
          "CHECKS": [],
          "IS_PRIMARY": false,
          "IS_INDEX": false,
          "VALUES": [
            "ceo",
            "admin",
            "accounts_head",
            "dept_head",
            "employee",
            "volunteer"
          ],
          "COMMENT": null
        }
      },
      "PRIMARY_KEYS": [
        "role_id"
      ],
      "FOREIGN_KEYS": [],
      "CHECKS": [],
      "INDEXES": [],
      "COMMENT": null
    },
    "salaries": {
      "COLUMNS": {
        "emp_no": {
          "TYPE": "Int",
          "NULLABLE": false,
          "UNIQUE": null,
          "DEFAULT": null,
          "CHECKS": [],
          "IS_PRIMARY": false,
          "IS_INDEX": false,
          "COMMENT": null
        },
        "salary": {
          "TYPE": "Int",
          "NULLABLE": false,
          "UNIQUE": null,
          "DEFAULT": null,
          "CHECKS": [],
          "IS_PRIMARY": false,
          "IS_INDEX": false,
          "COMMENT": null
        },
        "from_date": {
          "TYPE": "Date",
          "NULLABLE": false,
          "UNIQUE": null,
          "DEFAULT": null,
          "CHECKS": [],
          "IS_PRIMARY": false,
          "IS_INDEX": false,
          "COMMENT": null
        },
        "to_date": {
          "TYPE": "Date",
          "NULLABLE": false,
          "UNIQUE": null,
          "DEFAULT": null,
          "CHECKS": [],
          "IS_PRIMARY": false,
          "IS_INDEX": false,
          "COMMENT": null
        }
      },
      "PRIMARY_KEYS": [],
      "FOREIGN_KEYS": [],
      "CHECKS": [],
      "INDEXES": [],
      "COMMENT": null
    },
    "teaching_staff": {
      "COLUMNS": {
        "teaching_id": {
          "TYPE": "Int",
          "NULLABLE": false,
          "UNIQUE": null,
          "DEFAULT": null,
          "CHECKS": [],
          "IS_PRIMARY": false,
          "IS_INDEX": false,
          "COMMENT": null
        },
        "program_staff_id": {
          "TYPE": "Int",
          "NULLABLE": false,
          "UNIQUE": null,
          "DEFAULT": null,
          "CHECKS": [],
          "IS_PRIMARY": false,
          "IS_INDEX": false,
          "COMMENT": null
        },
        "teaching": {
          "TYPE": "Varchar",
          "NULLABLE": false,
          "UNIQUE": null,
          "DEFAULT": null,
          "CHECKS": [],
          "IS_PRIMARY": false,
          "IS_INDEX": false,
          "COMMENT": null
        },
        "created_on": {
          "TYPE": "Int",
          "NULLABLE": false,
          "UNIQUE": null,
          "DEFAULT": null,
          "CHECKS": [],
          "IS_PRIMARY": false,
          "IS_INDEX": false,
          "COMMENT": null
        },
        "updated_on": {
          "TYPE": "Int",
          "NULLABLE": false,
          "UNIQUE": null,
          "DEFAULT": null,
          "CHECKS": [],
          "IS_PRIMARY": false,
          "IS_INDEX": false,
          "COMMENT": null
        }
      },
      "PRIMARY_KEYS": [],
      "FOREIGN_KEYS": [
        {
          "COLUMNS": [
            "program_staff_id"
          ],
          "FOREIGN_TABLE": "program_staff",
          "REFERRED_COLUMNS": [
            "program_staff_id"
          ],
          "ON_DELETE": "Cascade",
          "ON_UPDATE": null
        }
      ],
      "CHECKS": [],
      "INDEXES": [],
      "COMMENT": null
    },
    "titles": {
      "COLUMNS": {
        "title_id": {
          "TYPE": "Int",
          "NULLABLE": false,
          "UNIQUE": true,
          "DEFAULT": null,
          "CHECKS": [],
          "IS_PRIMARY": true,
          "IS_INDEX": false,
          "VALUES": [
            1,
            2,
            3,
            4
          ],
          "COMMENT": null
        },
        "title": {
          "TYPE": "Varchar",
          "NULLABLE": false,
          "UNIQUE": null,
          "DEFAULT": null,
          "CHECKS": [],
          "IS_PRIMARY": false,
          "IS_INDEX": false,
          "VALUES": [
            "Agriculture.",
            "Biological and Biomedical Sciences",
            "children_program 1",
            "children_program 2"
          ],
          "COMMENT": null
        },
        "created_on": {
          "TYPE": "Datetime",
          "NULLABLE": false,
          "UNIQUE": null,
          "DEFAULT": null,
          "CHECKS": [],
          "IS_PRIMARY": false,
          "IS_INDEX": false,
          "VALUES": [
            "0000-00-00 00:00:00",
            "0000-00-00 00:00:00",
            "0000-00-00 00:00:00",
            "0000-00-00 00:00:00"
          ],
          "COMMENT": null
        },
        "updated_on": {
          "TYPE": "Datetime",
          "NULLABLE": false,
          "UNIQUE": null,
          "DEFAULT": null,
          "CHECKS": [],
          "IS_PRIMARY": false,
          "IS_INDEX": false,
          "VALUES": [
            "0000-00-00 00:00:00",
            "0000-00-00 00:00:00",
            "0000-00-00 00:00:00",
            "0000-00-00 00:00:00"
          ],
          "COMMENT": null
        },
        "dept_id": {
          "TYPE": "Int",
          "NULLABLE": false,
          "UNIQUE": null,
          "DEFAULT": null,
          "CHECKS": [],
          "IS_PRIMARY": false,
          "IS_INDEX": false,
          "VALUES": [
            3,
            3,
            2,
            2
          ],
          "COMMENT": null
        }
      },
      "PRIMARY_KEYS": [
        "title_id"
      ],
      "FOREIGN_KEYS": [],
      "CHECKS": [],
      "INDEXES": [],
      "COMMENT": null
    }
  }
}