{
  "INFO": {
    "URL": "https://github.com/pesse/sith-demo-db/blob/7e1344c7d0082404b54cd795174c86155ac28124/dbobjects/table/groups.sql?raw=true\n",
    "LICENSE": "MIT",
    "PERMISSIVE": true
  },
  "TABLES": {
    "groups": {
      "COLUMNS": {
        "id": {
          "TYPE": "Int",
          "NULLABLE": false,
          "UNIQUE": true,
          "DEFAULT": null,
          "CHECKS": [],
          "IS_PRIMARY": true,
          "IS_INDEX": false,
          "COMMENT": null
        },
        "group_type_fk": {
          "TYPE": "Int",
          "NULLABLE": false,
          "UNIQUE": true,
          "DEFAULT": null,
          "CHECKS": [],
          "IS_PRIMARY": false,
          "IS_INDEX": false,
          "COMMENT": null
        },
        "nr_in_group": {
          "TYPE": "Int",
          "NULLABLE": false,
          "UNIQUE": true,
          "DEFAULT": null,
          "CHECKS": [],
          "IS_PRIMARY": false,
          "IS_INDEX": false,
          "COMMENT": null
        },
        "parent_fk": {
          "TYPE": "Int",
          "NULLABLE": null,
          "UNIQUE": true,
          "DEFAULT": null,
          "CHECKS": [],
          "IS_PRIMARY": false,
          "IS_INDEX": false,
          "COMMENT": null
        },
        "honor_name": {
          "TYPE": "varchar2",
          "NULLABLE": null,
          "UNIQUE": null,
          "DEFAULT": null,
          "CHECKS": [],
          "IS_PRIMARY": false,
          "IS_INDEX": false,
          "COMMENT": null
        }
      },
      "PRIMARY_KEYS": [
        "id"
      ],
      "FOREIGN_KEYS": [
        {
          "COLUMNS": [
            "parent_fk"
          ],
          "FOREIGN_TABLE": "groups",
          "REFERRED_COLUMNS": [
            "id"
          ],
          "ON_DELETE": "SetNull",
          "ON_UPDATE": null
        }
      ],
      "CHECKS": [],
      "INDEXES": [],
      "COMMENT": null
    }
  }
}